{"driverName":"alvin wong","displayName":"Alvin Wong","driverId":"alvin-wong","score":47,"rank":7436,"primaryClass":"Street Touring Street ","allClasses":["Street Touring Street "],"region":"San Diego Region (#57)","consistency":3,"trend":"absent","dataPoints":1,"confidence":1,"eventCount":1,"yearScores":{},"lastEvent":"2001-03-17T08:00:00.000Z","nationalsWins":0,"regions":["San Diego Region (#57)"],"cars":["99 Honda Civic blue"],"tires":["Yokohama"],"cities":["San Diego, CA"],"history":[{"eventCode":"2001-San-Diego-National-Tour","eventName":"2001 San Diego National Tour","eventDates":"March 17, 2001 - March 18, 2001 in San Diego, CA","eventType":"tour","className":"Street Touring Street ","position":7,"totalInClass":9,"paxTime":162.165,"trophy":false,"car":"99 Honda Civic blue","carNumber":"69","tire":"Yokohama"}]}