{"driverName":"andrew bolasky","displayName":"Andrew Bolasky","driverId":"andrew-bolasky","score":55,"rank":5505,"primaryClass":"E Street","allClasses":["E Street"],"region":"","consistency":2,"trend":"absent","dataPoints":2,"confidence":2,"eventCount":2,"yearScores":{"2018":50},"lastEvent":"2018-06-08T07:00:00.000Z","nationalsWins":0,"regions":[],"cars":["1999 Mazda Miata"],"tires":["Bridgestone"],"cities":["Fogelsville, PA"],"history":[{"eventCode":"2018-Finger-Lakes-National-Tour","eventName":"2018 Finger Lakes National Tour","eventDates":"June 8, 2018 - June 10, 2018 in Romulus, NY","eventType":"tour","className":"E Street","position":11,"totalInClass":14,"paxTime":131.548,"trophy":false,"car":"1999 Mazda Miata","carNumber":"58","tire":"Bridgestone","paxOverallPosition":148,"paxOverallTotal":245},{"eventCode":"2018-Pittsburgh-Match-Tour","eventName":"2018 Pittsburgh Match Tour","eventDates":"April 27, 2018 - April 29, 2018 in Wampum, PA","eventType":"tour","className":"E Street","position":2,"totalInClass":5,"paxTime":107.407,"trophy":true,"car":"1999 Mazda Miata","carNumber":"58","tire":"Bridgestone","paxOverallPosition":67,"paxOverallTotal":180}]}