{"driverName":"christopher fran","displayName":"Christopher Fran","driverId":"christopher-fran","score":55,"rank":5352,"primaryClass":"B Stock","allClasses":["B Stock"],"region":"New England Region (#22)","consistency":3,"trend":"absent","dataPoints":1,"confidence":1,"eventCount":1,"yearScores":{},"lastEvent":"2000-06-09T00:00:00.000Z","regions":["New England Region (#22)"],"cars":["99 Mazda Miata Green"],"tires":["Kumho"],"cities":["Vernon, CT"],"history":[{"eventCode":"2000-Ayer-National-Tour","eventName":"2000 Ayer National Tour","eventDates":"June 9, 2000 - June 11, 2000 in Ayer, MA","eventType":"tour","className":"B Stock","position":11,"totalInClass":15,"paxTime":123.16,"trophy":false,"car":"99 Mazda Miata Green","carNumber":"2","tire":"Kumho","paxOverallPosition":96,"paxOverallTotal":187}]}