{"driverName":"colin faucett","displayName":"Colin Faucett","driverId":"colin-faucett","score":66,"rank":2212,"primaryClass":"C Modified","allClasses":["C Modified","B Stock"],"region":"Indianapolis Region (#13)","consistency":1,"trend":"absent","dataPoints":4,"confidence":3,"eventCount":6,"yearScores":{"2012":36,"2015":44,"2016":67,"2017":59},"lastEvent":"2017-06-02T00:00:00.000Z","regions":["Indianapolis Region (#13)"],"cars":["2009 Nissan 370Z Nismo","VanDiemen*","1984 Van Diemen* Rf84","Van Dieman RF84","Van Diemen","1984 Van Diemen"],"tires":["Hoosier"],"cities":["Granger, IN","Brownsburg, IN"],"history":[{"eventCode":"2017-Peru-Match-Tour","eventName":"2017 Peru Match Tour","eventDates":"June 2, 2017 - June 4, 2017 in Grissom, IN","eventType":"tour","className":"C Modified","position":5,"totalInClass":5,"paxTime":87.543,"trophy":false,"car":"1984 Van Diemen","carNumber":"91","tire":"Hoosier","paxOverallPosition":68,"paxOverallTotal":160},{"eventCode":"2016-SCCA-Solo-Nationals","eventName":"2016 SCCA Solo Nationals","eventDates":"September 6, 2016 - September 9, 2016 in Lincoln, NE","eventType":"nationals","className":"C Modified","position":14,"totalInClass":26,"paxTime":107.127,"trophy":false,"car":"Van Dieman RF84","carNumber":"191","tire":"Hoosier","paxOverallPosition":201,"paxOverallTotal":1126},{"eventCode":"2016-Wilmington-National-Tour","eventName":"2016 Wilmington National Tour","eventDates":"July 22, 2016 - July 24, 2016 in Wilmington, OH","eventType":"tour","className":"C Modified","position":2,"totalInClass":9,"paxTime":132.58,"trophy":true,"car":"Van Diemen","carNumber":"91","tire":"Hoosier","paxOverallPosition":93,"paxOverallTotal":308},{"eventCode":"2015-SCCA-Solo-Nationals","eventName":"2015 SCCA Solo Nationals","eventDates":"September 8, 2015 - September 11, 2015 in Lincoln, NE","eventType":"nationals","className":"C Modified","position":14,"totalInClass":19,"paxTime":122.356,"trophy":false,"car":"VanDiemen*","carNumber":"191","tire":"Hoosier","paxOverallPosition":985,"paxOverallTotal":1053},{"eventCode":"2015-Wilmington-National-Tour","eventName":"2015 Wilmington National Tour","eventDates":"August 14, 2015 - August 16, 2015 in Wilmington, OH","eventType":"tour","className":"C Modified","position":5,"totalInClass":9,"paxTime":128.664,"trophy":false,"car":"1984 Van Diemen* Rf84","carNumber":"191","tire":"Hoosier","paxOverallPosition":220,"paxOverallTotal":332},{"eventCode":"2012-Peru-National-Tour","eventName":"2012 Peru National Tour","eventDates":"August 4, 2012 - August 5, 2012 in Peru, IN","eventType":"tour","className":"B Stock","position":4,"totalInClass":5,"paxTime":115.439,"trophy":false,"car":"2009 Nissan 370Z Nismo","carNumber":"19","tire":"Hoosier","paxOverallPosition":213,"paxOverallTotal":231}]}