{"driverName":"don mertens","displayName":"Don Mertens","driverId":"don-mertens","score":51,"rank":4215,"primaryClass":"Street Touring Xtreme","allClasses":["Street Touring Xtreme"],"region":"St Louis Region (#21)","consistency":3,"trend":"absent","dataPoints":1,"confidence":1,"eventCount":1,"yearScores":{"2012":47},"lastEvent":"2012-11-10T08:00:00.000Z","regions":["St Louis Region (#21)"],"cars":["2005 Subaru WRX"],"tires":["Dunlop"],"cities":["Saint Louis, MO"],"history":[{"eventCode":"2012-St-Louis-National-Tour","eventName":"2012 St Louis National Tour","eventDates":"November 10, 2012 - November 11, 2012 in St Louis, MO","eventType":"tour","className":"Street Touring Xtreme","position":8,"totalInClass":11,"paxTime":141.642,"trophy":false,"car":"2005 Subaru WRX","carNumber":"22","tire":"Dunlop","paxOverallPosition":24,"paxOverallTotal":51}]}