{"driverName":"jeffrey lundgren","displayName":"Jeff Lundgren","driverId":"jeffrey-lundgren","score":56,"rank":5076,"primaryClass":"C Street","allClasses":["C Street","D Stock","Super Stock"],"region":"Kansas City Region (#16)","consistency":5,"trend":"absent","dataPoints":5,"confidence":5,"eventCount":16,"yearScores":{"2010":41,"2023":42,"2024":42},"lastEvent":"2024-09-02T07:00:00.000Z","nationalsWins":0,"regions":["Kansas City Region (#16)","Colorado Region (#8)","Utah Region (#50)"],"cars":["1997 Acura Integra Red","1997 Acura Integra GS-4","2002 Chevrolet Corvette","2002 Chevrolet Vette Z06","2002 Chevrolet Vette Z06 Red","2002 Chevrolet Corvette Z0","2006 Lotus Elise","2009 Subaru WRX","2022 Mazda Miata"],"tires":["Kumho","Hoosier","Yokohama","Bridgestone"],"cities":["Kansas City, MO","Castle Rock, CO","Pleasant View, UT","Salt Lake City, UT","South Salt Lake, UT"],"history":[{"eventCode":"2024-SCCA-Solo-Nationals","eventName":"2024 SCCA Solo Nationals","eventDates":"September 2, 2024 - September 6, 2024 in Lincoln, NE","eventType":"nationals","className":"C Street","position":45,"totalInClass":59,"paxTime":126.981,"trophy":false,"car":"2022 Mazda Miata","carNumber":"83","tire":"Bridgestone","paxOverallPosition":791,"paxOverallTotal":1085},{"eventCode":"2023-SCCA-Solo-Nationals","eventName":"2023 SCCA Solo Nationals","eventDates":"September 5, 2023 - September 8, 2023 in Lincoln, NE","eventType":"nationals","className":"C Street","position":46,"totalInClass":56,"paxTime":126.25,"trophy":false,"car":"2022 Mazda Miata","carNumber":"21","tire":"Bridgestone","paxOverallPosition":842,"paxOverallTotal":1122},{"eventCode":"2023-Las-Vegas-National-Tour","eventName":"2023 Las Vegas National Tour","eventDates":"March 31, 2023 - April 2, 2023 in Las Vegas, NV","eventType":"tour","className":"C Street","position":4,"totalInClass":8,"paxTime":113.219,"trophy":false,"car":"2022 Mazda Miata","carNumber":"21","tire":"Yokohama","paxOverallPosition":95,"paxOverallTotal":133},{"eventCode":"2010-Wendover-National-Tour","eventName":"2010 Wendover National Tour","eventDates":"May 14, 2010 - May 16, 2010 in Wendover, UT","eventType":"tour","className":"D Stock","position":5,"totalInClass":5,"paxTime":109.313,"trophy":false,"car":"2009 Subaru WRX","carNumber":"85","tire":"Hoosier","paxOverallPosition":86,"paxOverallTotal":122},{"eventCode":"2009-Vail-National-Tour","eventName":"2009 Vail National Tour","eventDates":"August 1, 2009 - August 2, 2009 in Vail, CO","eventType":"tour","className":"D Stock","position":6,"totalInClass":6,"paxTime":99.862,"trophy":false,"car":"2009 Subaru WRX","carNumber":"85","tire":"Hoosier","paxOverallPosition":80,"paxOverallTotal":150},{"eventCode":"2008-SCCA-Solo-Nationals","eventName":"2008 SCCA Solo Nationals","eventDates":"September 16, 2008 - September 19, 2008 in Topeka, KS","eventType":"nationals","className":"Super Stock","position":26,"totalInClass":57,"paxTime":83.882,"trophy":false,"car":"2006 Lotus Elise","carNumber":"59","tire":"Hoosier","paxOverallPosition":365,"paxOverallTotal":853},{"eventCode":"2007-SCCA-Solo-Nationals","eventName":"2007 SCCA Solo Nationals","eventDates":"September 25, 2007 - September 29, 2007 in Topeka, KS","eventType":"nationals","className":"Super Stock","position":26,"totalInClass":67,"paxTime":92.872,"trophy":false,"car":"2006 Lotus Elise","carNumber":"185","tire":"Hoosier","paxOverallPosition":363,"paxOverallTotal":933},{"eventCode":"2006-SCCA-Solo-Nationals","eventName":"2006 SCCA Solo Nationals","eventDates":"September 4, 2006 - September 8, 2006 in Topeka, KS","eventType":"nationals","className":"Super Stock","position":20,"totalInClass":61,"paxTime":103.063,"trophy":false,"car":"2006 Lotus Elise","carNumber":"85","tire":"Hoosier","paxOverallPosition":206,"paxOverallTotal":870},{"eventCode":"2006-Denver-National-Tour","eventName":"2006 Denver National Tour","eventDates":"July 15, 2006 - July 16, 2006 in Denver, CO","eventType":"tour","className":"Super Stock","position":3,"totalInClass":11,"paxTime":103.619,"trophy":true,"car":"2006 Lotus Elise","carNumber":"85","tire":"Hoosier","paxOverallPosition":38,"paxOverallTotal":163},{"eventCode":"2005-SCCA-Solo-Nationals","eventName":"2005 SCCA Solo Nationals","eventDates":"September 13, 2005 - September 16, 2005 in Topeka, KS","eventType":"nationals","className":"Super Stock","position":27,"totalInClass":56,"paxTime":125.574,"trophy":false,"car":"2002 Chevrolet Corvette Z0","carNumber":"31","tire":"Kumho","paxOverallPosition":724,"paxOverallTotal":892},{"eventCode":"2005-Denver-National-Tour","eventName":"2005 Denver National Tour","eventDates":"July 30, 2005 - July 31, 2005 in Denver, CO","eventType":"tour","className":"Super Stock","position":3,"totalInClass":10,"paxTime":137.138,"trophy":true,"car":"2002 Chevrolet Corvette Z0","carNumber":"31","tire":"Kumho","paxOverallPosition":38,"paxOverallTotal":211},{"eventCode":"2004-SCCA-Solo-Nationals","eventName":"2004 SCCA Solo Nationals","eventDates":"September 14, 2004 - September 17, 2004 in Topeka, KS","eventType":"nationals","className":"Super Stock","position":19,"totalInClass":46,"paxTime":99.2,"trophy":false,"car":"2002 Chevrolet Vette Z06 Red","carNumber":"13","tire":"Kumho","paxOverallPosition":205,"paxOverallTotal":862},{"eventCode":"2003-SCCA-Solo-Nationals","eventName":"2003 SCCA Solo Nationals","eventDates":"September 9, 2003 - September 12, 2003 in Topeka, KS","eventType":"nationals","className":"Super Stock","position":30,"totalInClass":43,"paxTime":121.05,"trophy":false,"car":"2002 Chevrolet Vette Z06","carNumber":"131","tire":"Hoosier","paxOverallPosition":750,"paxOverallTotal":851},{"eventCode":"2002-SCCA-Solo-Nationals","eventName":"2002 SCCA Solo Nationals","eventDates":"September 10, 2002 - September 13, 2002 in Topeka, KS","eventType":"nationals","className":"Super Stock","position":31,"totalInClass":52,"paxTime":100.128,"trophy":false,"car":"2002 Chevrolet Corvette","carNumber":"131","tire":"Hoosier","paxOverallPosition":416,"paxOverallTotal":879},{"eventCode":"2001-SCCA-Solo-Nationals","eventName":"2001 SCCA Solo Nationals","eventDates":"September 10, 2001 - September 14, 2001 in Topeka, KS","eventType":"nationals","className":"Street Modified","position":29,"totalInClass":43,"paxTime":53.167,"trophy":false,"car":"1997 Acura Integra GS-4","carNumber":"32","tire":"Kumho","paxOverallPosition":648,"paxOverallTotal":852},{"eventCode":"2000-SCCA-Solo-Nationals","eventName":"2000 SCCA Solo Nationals","eventDates":"September 11, 2000 - September 15, 2000 in Topeka, KS","eventType":"nationals","className":"Street Modified","position":18,"totalInClass":20,"paxTime":119.024,"trophy":false,"car":"1997 Acura Integra Red","carNumber":"31","tire":"Kumho","paxOverallPosition":914,"paxOverallTotal":953}]}