{"driverName":"jeffrey kanetzky","displayName":"Jeff Kanetzky","driverId":"jeffrey-kanetzky","score":44,"rank":8421,"primaryClass":"Street Touring Xtreme","allClasses":["Street Touring Xtreme"],"region":"Mohawk Hudson Region (#65)","consistency":3,"trend":"absent","dataPoints":2,"confidence":1,"eventCount":1,"yearScores":{},"lastEvent":"2008-06-07T00:00:00.000Z","regions":["Mohawk Hudson Region (#65)"],"cars":["1998 BMW 381ti"],"tires":["Bridgestone"],"cities":["Schenectady, NY"],"history":[{"eventCode":"2008-Devens-National-Tour","eventName":"2008 Devens National Tour","eventDates":"June 7, 2008 - June 8, 2008 in Ayer, MA","eventType":"tour","className":"Street Touring Xtreme","position":9,"totalInClass":10,"paxTime":129.11,"trophy":false,"car":"1998 BMW 381ti","carNumber":"147","tire":"Bridgestone","paxOverallPosition":148,"paxOverallTotal":203}]}