{"driverName":"lawrence alger","displayName":"Larry Alger","driverId":"lawrence-alger","score":37,"rank":10710,"primaryClass":"E Stock","allClasses":["E Stock"],"region":"Iowa Region (#14)","consistency":3,"trend":"absent","dataPoints":3,"confidence":2,"eventCount":1,"yearScores":{},"lastEvent":"1998-09-14T07:00:00.000Z","nationalsWins":0,"regions":["Iowa Region (#14)"],"cars":["1998 Dodge Neon Red"],"tires":["BFGoodrich"],"cities":["Cedar Falls, IA"],"history":[{"eventCode":"1998-SCCA-Solo-Nationals","eventName":"1998 SCCA Solo Nationals","eventDates":"September 14, 1998 - September 18, 1998 in Topeka, KS","eventType":"nationals","className":"E Stock","position":26,"totalInClass":30,"paxTime":121.85,"trophy":false,"car":"1998 Dodge Neon Red","carNumber":"88","tire":"BFGoodrich","paxOverallPosition":623,"paxOverallTotal":737}]}