{"driverName":"manny papandreas","displayName":"Manny Papandreas","driverId":"manny-papandreas","score":53,"rank":6036,"primaryClass":"B Street Prepared","allClasses":["B Street Prepared","F Modified","Super Stock"],"region":"Northwestern Ohio Region (#28)","consistency":2,"trend":"absent","dataPoints":4,"confidence":3,"eventCount":4,"yearScores":{},"lastEvent":"1998-09-14T00:00:00.000Z","regions":["Northwestern Ohio Region (#28)"],"cars":["1993 Chevrolet Corvette Maroon","1983 Chevrolet Corvette Ma","1987 Red Devil 87-01 While","1971 Chevy Corvette White/Green"],"tires":["BFGoodrich","Hoosier"],"cities":["Indianapolis, IN"],"history":[{"eventCode":"1998-SCCA-Solo-Nationals","eventName":"1998 SCCA Solo Nationals","eventDates":"September 14, 1998 - September 18, 1998 in Topeka, KS","eventType":"nationals","className":"B Street Prepared","position":18,"totalInClass":22,"paxTime":113.153,"trophy":false,"car":"1971 Chevy Corvette White/Green","carNumber":"22","tire":"Hoosier","paxOverallPosition":628,"paxOverallTotal":737},{"eventCode":"1997-SCCA-Solo-Nationals","eventName":"1997 SCCA Solo Nationals","eventDates":"September 8, 1997 - September 12, 1997 in Topeka, KS","eventType":"nationals","className":"F Modified","position":15,"totalInClass":23,"paxTime":105.578,"trophy":false,"car":"1987 Red Devil 87-01 While","carNumber":"31","tire":"Hoosier","paxOverallPosition":527,"paxOverallTotal":729},{"eventCode":"1996-SCCA-Solo-Nationals","eventName":"1996 SCCA Solo Nationals","eventDates":"September 10, 1996 - September 13, 1996 in Topeka, KS","eventType":"nationals","className":"Super Stock","position":18,"totalInClass":42,"paxTime":114.052,"trophy":false,"car":"1983 Chevrolet Corvette Ma","carNumber":"81","tire":"Hoosier","paxOverallPosition":235,"paxOverallTotal":592},{"eventCode":"1995-SCCA-Solo-Nationals","eventName":"1995 SCCA Solo Nationals","eventDates":"September 4, 1995 - September 8, 1995 in Topeka, KS","eventType":"nationals","className":"Super Stock","position":21,"totalInClass":42,"paxTime":119.379,"trophy":false,"car":"1993 Chevrolet Corvette Maroon","carNumber":"81","tire":"BFGoodrich","paxOverallPosition":328,"paxOverallTotal":567}]}