{"driverName":"thomas carlin","displayName":"Tom Carlin","driverId":"thomas-carlin","score":27,"rank":12732,"primaryClass":"A Stock","allClasses":["A Stock","X Prepared"],"region":"Colorado Region (#8)","consistency":3,"trend":"absent","dataPoints":1,"confidence":1,"eventCount":1,"yearScores":{},"lastEvent":"2009-08-01T00:00:00.000Z","regions":["Colorado Region (#8)"],"cars":["2003 Porsche Boxster S","1972 Porsche 914"],"tires":["Bridgestone","N/A"],"cities":["Eagle, CO"],"history":[{"eventCode":"2009-Vail-National-Tour","eventName":"2009 Vail National Tour","eventDates":"August 1, 2009 - August 2, 2009 in Vail, CO","eventType":"tour","className":"A Stock","position":5,"totalInClass":5,"paxTime":111.003,"trophy":false,"car":"2003 Porsche Boxster S","carNumber":"16","tire":"Bridgestone","paxOverallPosition":150,"paxOverallTotal":150},{"eventCode":"2009-Vail-National-Tour","eventName":"2009 Vail National Tour","eventDates":"August 1, 2009 - August 2, 2009 in Vail, CO","eventType":"tour","className":"X Prepared","position":5,"totalInClass":5,"paxTime":124.013,"trophy":false,"car":"1972 Porsche 914","carNumber":"89","tire":"N/A"}]}